NLP_ex_1/ex1.py
NLP_ex_1/ex2.py
NLP_ex_1/ex3.py
NLP_ex_1/ex4.py
NLP_ex_1/ex5.py
NLP_ex_1-0.0.0.2.dist-info/METADATA
NLP_ex_1-0.0.0.2.dist-info/WHEEL
NLP_ex_1-0.0.0.2.dist-info/top_level.txt
NLP_ex_1-0.0.0.2.dist-info/RECORD
