Metadata-Version: 2.1
Name: NLP-ex-1
Version: 0.0.0.2
Summary: NLP_ex_1
Home-page: https://lingua.blog.me/...
Author: MinHeum Lee
Author-email: alsgma112@naver.com
License: MIT
Platform: UNKNOWN
Requires-Python: >=3
